py_plan/__init__.py
py_plan/base.py
py_plan/pattern_matching.py
py_plan/total_order.py
py_plan/unification.py
py_plan/problems/air_cargo.py
py_plan/problems/blocksworld.py
py_plan/problems/book_ordering.py
py_plan/problems/math_example.py
py_plan/problems/spare_tire.py
py_plan-1.0.0.dist-info/LICENSE.txt
py_plan-1.0.0.dist-info/METADATA
py_plan-1.0.0.dist-info/WHEEL
py_plan-1.0.0.dist-info/pbr.json
py_plan-1.0.0.dist-info/top_level.txt
py_plan-1.0.0.dist-info/RECORD
