Metadata-Version: 2.1
Name: py-plan
Version: 1.0.0
Summary: A library of propositional and relational planning algorithms.
Home-page: https://pypi.python.org/pypi/py_plan/
Author: Christopher J. MacLellan
Author-email: maclellan.christopher@gmail.com
License: MIT
Project-URL: Source Code, https://github.com/cmaclell/py_plan
Platform: UNKNOWN
Classifier: Development Status :: 4 - Beta
Classifier: Intended Audience :: Science/Research
Classifier: Topic :: Scientific/Engineering :: Artificial Intelligence
Classifier: License :: OSI Approved :: MIT License
Classifier: Programming Language :: Python
Classifier: Programming Language :: Python :: 2
Classifier: Programming Language :: Python :: 2.7
Classifier: Programming Language :: Python :: 3
Classifier: Programming Language :: Python :: 3.7
Classifier: Programming Language :: Python :: Implementation :: PyPy
Requires-Dist: py-search
Requires-Dist: concept-formation
